logger/ConfigureLogger.py
logger/__init__.py
logger/conf/__init__.py
logger/conf/default-log-config.yaml
persuader_technology_automata_logger-0.0.5.dist-info/LICENSE
persuader_technology_automata_logger-0.0.5.dist-info/METADATA
persuader_technology_automata_logger-0.0.5.dist-info/WHEEL
persuader_technology_automata_logger-0.0.5.dist-info/top_level.txt
persuader_technology_automata_logger-0.0.5.dist-info/RECORD
