Metadata-Version: 2.1
Name: persuader-technology-automata-logger
Version: 0.0.5
Summary: Automata Logger
Author: Persuader Technology
Author-email: software@persuader.technology
License: UNLICENSE
Classifier: Programming Language :: Python :: 3
License-File: LICENSE
Requires-Dist: pyyaml (==6.0)
